hawk/__init__.py
hawk/py.typed
hawk/version.py
hawk/contrib/__init__.py
hawk/contrib/fastapi/__init__.py
hawk/contrib/fastapi/router.py
hawk/contrib/flask/__init__.py
hawk/contrib/flask/response.py
hawk/contrib/flask/router.py
hawk/contrib/starlette/__init__.py
hawk/contrib/starlette/middleware.py
hawk/contrib/starlette/response.py
hawk/contrib/starlette/router.py
hawk/expvars/__init__.py
hawk/expvars/vars.py
hawk/expvars/zpage.py
hawk/profiling/__init__.py
hawk/profiling/exceptions.py
hawk/profiling/profilers.py
hawk/profiling/renderers.py
hawk/profiling/trace_context.py
hawk/profiling/cpu/__init__.py
hawk/profiling/cpu/cprofile.py
hawk/profiling/cpu/pyinstrument.py
hawk/profiling/cpu/yappi.py
hawk/profiling/mem/__init__.py
hawk/profiling/mem/tracemalloc.py
hawk/profiling/thread/__init__.py
hawk/profiling/thread/threads.py
hawk/zpages/__init__.py
hawk/zpages/exceptions.py
hawk/zpages/page.py
hawk/zpages/routes.py
hawk/zpages/templates.py
hawk/zpages/theme.py
hawk/zpages/components/__init__.py
hawk/zpages/components/base.py
hawk/zpages/components/columns.py
hawk/zpages/components/container.py
hawk/zpages/components/header.py
hawk/zpages/components/subheader.py
hawk/zpages/components/tables.py
hawk/zpages/templates/footer.html.j2
hawk/zpages/templates/header.html.j2
hawk/zpages/templates/page.html.j2
hawk/zpages/templates/table.html.j2
hawk/zpages/templates/theme_toggle.html.j2
hawk_debug-0.0.3.dist-info/METADATA
hawk_debug-0.0.3.dist-info/WHEEL
hawk_debug-0.0.3.dist-info/licenses/LICENSE
hawk_debug-0.0.3.dist-info/RECORD
