Metadata-Version: 2.4
Name: hawk-debug
Version: 0.0.3
Summary: A debugging & profiling toolkit for production Python microservices
Author-email: Roman Glushko <roman.glushko.m@gmail.com>
License: MIT
License-File: LICENSE
Requires-Python: >=3.9
Provides-Extra: docs
Requires-Dist: mdx-include>=1.4.2; extra == 'docs'
Requires-Dist: mkautodoc>=0.2.0; extra == 'docs'
Requires-Dist: mkdocs-material>=9.5.34; extra == 'docs'
Requires-Dist: mkdocs-pymdownx-material-extras>=2.5.6; extra == 'docs'
Requires-Dist: mkdocs>=1.6.1; extra == 'docs'
Provides-Extra: pyinstrument
Requires-Dist: pyinstrument>=4.7.2; extra == 'pyinstrument'
Provides-Extra: yappi
Requires-Dist: yappi>=1.6.0; extra == 'yappi'
Provides-Extra: zpages
Requires-Dist: jinja2>=3.1.4; extra == 'zpages'
